kanban_indexer/__init__.py
kanban_indexer/alphabet_indexer.py
kanban_indexer/main.py
kanban_indexer-1.0.2.dist-info/LICENSE
kanban_indexer-1.0.2.dist-info/METADATA
kanban_indexer-1.0.2.dist-info/WHEEL
kanban_indexer-1.0.2.dist-info/top_level.txt
kanban_indexer-1.0.2.dist-info/RECORD
