Metadata-Version: 2.2
Name: kanban_indexer
Version: 1.0.2
Summary: A lexicographic indexing system for Kanban boards
Home-page: https://github.com/nickmccleery/kanban-indexer
Author: Nick McCleery
Author-email: contact@nickmccleery.com
Classifier: Programming Language :: Python :: 3
Classifier: License :: OSI Approved :: MIT License
Classifier: Operating System :: OS Independent
Requires-Python: >=3.6
License-File: LICENSE
Provides-Extra: dev
Requires-Dist: pytest==8.2.2; extra == "dev"
Requires-Dist: ruff==0.5.3; extra == "dev"
Requires-Dist: setuptools==74.1.2; extra == "dev"
Dynamic: author
Dynamic: author-email
Dynamic: classifier
Dynamic: description
Dynamic: description-content-type
Dynamic: home-page
Dynamic: provides-extra
Dynamic: requires-python
Dynamic: summary
